LICENSE
MANIFEST.in
README.md
setup.py
tc_redis/__init__.py
tc_redis/base_storage.py
tc_redis/utils.py
tc_redis.egg-info/PKG-INFO
tc_redis.egg-info/SOURCES.txt
tc_redis.egg-info/dependency_links.txt
tc_redis.egg-info/requires.txt
tc_redis.egg-info/top_level.txt
tc_redis/result_storages/__init__.py
tc_redis/result_storages/redis_result_storage.py
tc_redis/storages/__init__.py
tc_redis/storages/redis_storage.py
tests/__init__.py
tests/test_redis_cluster_result_storage.py
tests/test_redis_cluster_storage.py
tests/test_redis_result_storage.py
tests/test_redis_sentinel_result_storage.py
tests/test_redis_sentinel_storage.py
tests/test_redis_storage.py
tests/fixtures/__init__.py
tests/fixtures/storage_fixtures.py