Metadata-Version: 2.1
Name: tc-redis
Version: 2.3.0
Summary: Thumbor redis storage adapters
Home-page: https://github.com/thumbor-community/redis
Author: Thumbor Community
License: MIT
Keywords: thumbor redis
Platform: UNKNOWN
Classifier: Development Status :: 5 - Production/Stable
Classifier: License :: OSI Approved :: MIT License
Classifier: Programming Language :: Python :: 3
Provides-Extra: all
Provides-Extra: tests
License-File: LICENSE
